b32k/__init__.py
b32k/b32k.delta.jsonl
b32k/b32k.hashes.json
b32k/b32k.json
b32k/b32k.schema.json
b32k/b32k_canonical_alphabet.pdf
b32k/canon_hashes.py
b32k/codec.py
b32k/tools_ingest_from_csv.py
b32k-0.0.2.dist-info/METADATA
b32k-0.0.2.dist-info/WHEEL
b32k-0.0.2.dist-info/top_level.txt
b32k-0.0.2.dist-info/RECORD
