Metadata-Version: 2.4
Name: b32k
Version: 0.0.2
Summary: Canonical Base32768 (B32K) lattice + codec
Requires-Python: >=3.10
